gempadet/__init__.py
gempadet_indonesian-0.1.dist-info/LICENSE
gempadet_indonesian-0.1.dist-info/METADATA
gempadet_indonesian-0.1.dist-info/WHEEL
gempadet_indonesian-0.1.dist-info/top_level.txt
gempadet_indonesian-0.1.dist-info/RECORD
