Metadata-Version: 2.1
Name: gempadet-indonesian
Version: 0.1
Summary: this is an package of latest indonesian earthquake
Author: Muhammad Afrizal
Author-email: muhamadafrizal5@gmail.com
Keywords: python,video,stream,video stream,scream
Classifier: Programming Language :: Python :: 3
Classifier: Operating System :: Microsoft :: Windows
License-File: LICENSE
